odoo/addons/account_statement_import_online_stripe/README.rst
odoo/addons/account_statement_import_online_stripe/__init__.py
odoo/addons/account_statement_import_online_stripe/__manifest__.py
odoo/addons/account_statement_import_online_stripe/i18n/account_statement_import_online_stripe.pot
odoo/addons/account_statement_import_online_stripe/i18n/it.po
odoo/addons/account_statement_import_online_stripe/models/__init__.py
odoo/addons/account_statement_import_online_stripe/models/online_bank_statement_provider_stripe.py
odoo/addons/account_statement_import_online_stripe/readme/CONFIGURE.md
odoo/addons/account_statement_import_online_stripe/readme/CONTRIBUTORS.md
odoo/addons/account_statement_import_online_stripe/readme/DESCRIPTION.md
odoo/addons/account_statement_import_online_stripe/static/description/icon.png
odoo/addons/account_statement_import_online_stripe/static/description/index.html
odoo/addons/account_statement_import_online_stripe/tests/__init__.py
odoo/addons/account_statement_import_online_stripe/tests/test_online_bank_statement_provider_stripe.py
odoo/addons/account_statement_import_online_stripe/views/online_bank_statement_provider.xml
odoo_addon_account_statement_import_online_stripe-18.0.1.0.1.dist-info/METADATA
odoo_addon_account_statement_import_online_stripe-18.0.1.0.1.dist-info/WHEEL
odoo_addon_account_statement_import_online_stripe-18.0.1.0.1.dist-info/top_level.txt
odoo_addon_account_statement_import_online_stripe-18.0.1.0.1.dist-info/RECORD
